README.md
setup.py
query_domain_icp/__init__.py
query_domain_icp/miit.py
query_domain_icp.egg-info/PKG-INFO
query_domain_icp.egg-info/SOURCES.txt
query_domain_icp.egg-info/dependency_links.txt
query_domain_icp.egg-info/requires.txt
query_domain_icp.egg-info/top_level.txt