Metadata-Version: 2.1
Name: query-domain-icp
Version: 0.0.3
Summary: 获取域名 ICP 备案信息 自动破解滑动验证码 支持翻页
Home-page: https://github.com/qiangmouren/query-domain-icp-python
Author: StevenQ
License: UNKNOWN
Platform: UNKNOWN
